{
	"format_version": "1.21.6",
	"credit": "Made with Blockbench",
	"textures": {
		"lever": "block/lever",
		"particle": "block/particles/lever"
	},
	"elements": [
		{
			"from": [5, -0.02, 4],
			"to": [11, 2.98, 12],
			"faces": {
				"north": {"uv": [6, 8, 9, 14], "rotation": 90, "texture": "#lever"},
				"east": {"uv": [6, 0, 9, 8], "rotation": 90, "texture": "#lever"},
				"south": {"uv": [6, 8, 9, 14], "rotation": 90, "texture": "#lever"},
				"west": {"uv": [6, 0, 9, 8], "rotation": 90, "texture": "#lever"},
				"up": {"uv": [6, 8, 0, 0], "texture": "#lever"},
				"down": {"uv": [6, 8, 0, 16], "texture": "#lever", "cullface": "down"}
			}
		},
		{
			"from": [7, 1, 7],
			"to": [9, 11, 9],
			"rotation": {"angle": -45, "axis": "x", "origin": [8, 1, 8]},
			"faces": {
				"north": {"uv": [9, 0, 11, 10], "texture": "#lever"},
				"east": {"uv": [9, 0, 11, 10], "texture": "#lever"},
				"south": {"uv": [9, 0, 11, 10], "texture": "#lever"},
				"west": {"uv": [9, 0, 11, 10], "texture": "#lever"},
				"up": {"uv": [11, 2, 9, 0], "texture": "#lever"},
				"down": {"uv": [11, 0, 9, 2], "texture": "#lever"}
			}
		}
	]
}